MANIFEST.in
pyproject.toml
rolling_checksum_pyx_mod.c
rolling_checksum_pyx_mod.pyx
setup.py
rolling_checksum_pyx_mod.egg-info/PKG-INFO
rolling_checksum_pyx_mod.egg-info/SOURCES.txt
rolling_checksum_pyx_mod.egg-info/dependency_links.txt
rolling_checksum_pyx_mod.egg-info/requires.txt
rolling_checksum_pyx_mod.egg-info/top_level.txt