Metadata-Version: 1.1
Name: rolling-checksum-pyx-mod
Version: 1.1.3
Summary: Cython-augmented Python module providing a variable-length, content-based blocking algorithm
Home-page: http://stromberg.dnsalias.org/~dstromberg/rolling-checksum-mod/
Author: Daniel Richard Stromberg
Author-email: strombrg@gmail.com
License: GPLv3
Platform: Cross platform
Classifier: Development Status :: 5 - Production/Stable
Classifier: Intended Audience :: Developers
Classifier: Programming Language :: Cython
Classifier: Programming Language :: Python :: 3
